t8s/__about__.py
t8s/__init__.py
t8s/io.py
t8s/log_config.py
t8s/ts.py
t8s/ts_builder.py
t8s/ts_writer.py
t8s/util.py
t8s-0.1.17.dist-info/METADATA
t8s-0.1.17.dist-info/WHEEL
t8s-0.1.17.dist-info/licenses/LICENSE.txt
t8s-0.1.17.dist-info/RECORD
