Metadata-Version: 2.1
Name: t8s
Version: 0.1.17
Project-URL: Documentation, https://github.com/joao-parana/t8s#README.md
Project-URL: Issues, https://github.com/joao-parana/t8s/issues
Project-URL: Source, https://github.com/joao-parana/t8s
Author-email: João Antonio Ferreira <joao.parana@gmail.com>
License-Expression: MIT
License-File: LICENSE.txt
Classifier: Development Status :: 4 - Beta
Classifier: Programming Language :: Python
Classifier: Programming Language :: Python :: 3.10
Classifier: Programming Language :: Python :: 3.11
Classifier: Programming Language :: Python :: Implementation :: CPython
Classifier: Programming Language :: Python :: Implementation :: PyPy
Requires-Python: >=3.10
Requires-Dist: behave
Requires-Dist: behave-pandas
Requires-Dist: datafusion
Requires-Dist: keyring
Requires-Dist: keyrings-google-artifactregistry-auth
Requires-Dist: pandas
Requires-Dist: pyarrow
Requires-Dist: pyyaml
Requires-Dist: scikit-learn
Provides-Extra: dev
Requires-Dist: bandit; extra == 'dev'
Requires-Dist: black; extra == 'dev'
Requires-Dist: flake8; extra == 'dev'
Requires-Dist: hatch; extra == 'dev'
Requires-Dist: isort; extra == 'dev'
Requires-Dist: pylint; extra == 'dev'
Requires-Dist: pytest; extra == 'dev'
Requires-Dist: pytest-timeout; extra == 'dev'
